{
  "DataList": [
    {
      "UniqueId": 1,
      "MinDistance": 0.0,
      "MaxDistance": 0.0,
      "RotationX": 0.0,
      "RotationY": 0.0,
      "MoveInstantly": false,
      "LeftMargin": 2.836134169971986e+26,
      "BottomMargin": 1.912767751067873e+26,
      "IgnoreEnemies": false,
      "UseRailPointCompensation": false
    },
    {
      "UniqueId": 2,
      "MinDistance": 0.0,
      "MaxDistance": 0.0,
      "RotationX": 0.0,
      "RotationY": 0.0,
      "MoveInstantly": false,
      "LeftMargin": 2.836134169971986e+26,
      "BottomMargin": 1.912767751067873e+26,
      "IgnoreEnemies": false,
      "UseRailPointCompensation": false
    },
    {
      "UniqueId": 3,
      "MinDistance": 0.0,
      "MaxDistance": 0.0,
      "RotationX": 0.0,
      "RotationY": 0.0,
      "MoveInstantly": true,
      "LeftMargin": 2.9886996110435514e+24,
      "BottomMargin": 1.912767751067873e+26,
      "IgnoreEnemies": false,
      "UseRailPointCompensation": true
    },
    {
      "UniqueId": 4,
      "MinDistance": 0.0,
      "MaxDistance": 0.0,
      "RotationX": 0.0,
      "RotationY": 0.0,
      "MoveInstantly": false,
      "LeftMargin": 2.9886996110435514e+24,
      "BottomMargin": 1.912767751067873e+26,
      "IgnoreEnemies": false,
      "UseRailPointCompensation": true
    },
    {
      "UniqueId": 5,
      "MinDistance": 0.0,
      "MaxDistance": 0.0,
      "RotationX": 0.0,
      "RotationY": 0.0,
      "MoveInstantly": true,
      "LeftMargin": 2.9886996110435514e+24,
      "BottomMargin": 1.912767751067873e+26,
      "IgnoreEnemies": false,
      "UseRailPointCompensation": true
    },
    {
      "UniqueId": 6,
      "MinDistance": 0.0,
      "MaxDistance": 0.0,
      "RotationX": 0.0,
      "RotationY": 0.0,
      "MoveInstantly": true,
      "LeftMargin": 3.825535502135746e+26,
      "BottomMargin": 1.912767751067873e+26,
      "IgnoreEnemies": false,
      "UseRailPointCompensation": false
    },
    {
      "UniqueId": 7,
      "MinDistance": 0.0,
      "MaxDistance": 0.0,
      "RotationX": 0.0,
      "RotationY": 0.0,
      "MoveInstantly": true,
      "LeftMargin": 3.825535502135746e+26,
      "BottomMargin": 1.912767751067873e+26,
      "IgnoreEnemies": false,
      "UseRailPointCompensation": false
    },
    {
      "UniqueId": 8,
      "MinDistance": 0.0,
      "MaxDistance": 0.0,
      "RotationX": 0.0,
      "RotationY": 0.0,
      "MoveInstantly": true,
      "LeftMargin": 2.836134169971986e+26,
      "BottomMargin": 3.138727758604909e+25,
      "IgnoreEnemies": false,
      "UseRailPointCompensation": false
    },
    {
      "UniqueId": 9,
      "MinDistance": 0.0,
      "MaxDistance": 0.0,
      "RotationX": 0.0,
      "RotationY": 0.0,
      "MoveInstantly": false,
      "LeftMargin": 2.836134169971986e+26,
      "BottomMargin": 1.912767751067873e+26,
      "IgnoreEnemies": true,
      "UseRailPointCompensation": false
    },
    {
      "UniqueId": 10,
      "MinDistance": 0.0,
      "MaxDistance": 0.0,
      "RotationX": 0.0,
      "RotationY": 0.0,
      "MoveInstantly": false,
      "LeftMargin": 2.9886996110435514e+24,
      "BottomMargin": 1.912767751067873e+26,
      "IgnoreEnemies": false,
      "UseRailPointCompensation": false
    }
  ]
}